README.md
setup.py
BDSSeleniumLibrary/__init__.py
BDSSeleniumLibrary.egg-info/PKG-INFO
BDSSeleniumLibrary.egg-info/SOURCES.txt
BDSSeleniumLibrary.egg-info/dependency_links.txt
BDSSeleniumLibrary.egg-info/requires.txt
BDSSeleniumLibrary.egg-info/top_level.txt
BDSSeleniumLibrary/Core/BDSLibraryComponent.py
BDSSeleniumLibrary/Core/__init__.py
BDSSeleniumLibrary/Keywords/AdvancedDropdown.py
BDSSeleniumLibrary/Keywords/CheckBox.py
BDSSeleniumLibrary/Keywords/ClickableElement.py
BDSSeleniumLibrary/Keywords/DatetimeInput.py
BDSSeleniumLibrary/Keywords/DatetimePicker.py
BDSSeleniumLibrary/Keywords/FancyBox.py
BDSSeleniumLibrary/Keywords/FileInput.py
BDSSeleniumLibrary/Keywords/Input.py
BDSSeleniumLibrary/Keywords/MultipleDropdown.py
BDSSeleniumLibrary/Keywords/Radio.py
BDSSeleniumLibrary/Keywords/SingleDropdown.py
BDSSeleniumLibrary/Keywords/Table.py
BDSSeleniumLibrary/Keywords/TableImage.py
BDSSeleniumLibrary/Keywords/TableText.py
BDSSeleniumLibrary/Keywords/Text.py
BDSSeleniumLibrary/Keywords/TextArea.py
BDSSeleniumLibrary/Keywords/__init__.py