Metadata-Version: 2.1
Name: BDSSeleniumLibrary
Version: 0.0.4
Summary: A small example package
Home-page: https://git.batdongsan.com.vn/DuongNT4/MSV_Batdongsan_Automation_Testing
Author: kinhnv
Author-email: kinhnv@batdongsan.com.vn
License: UNKNOWN
Platform: UNKNOWN
Classifier: Programming Language :: Python :: 3
Classifier: License :: OSI Approved :: MIT License
Classifier: Operating System :: OS Independent
Requires-Python: >=3.7
